uniformbands/__init__.py
uniformbands/_base.py
uniformbands/_methods.py
uniformbands-0.1.0.dist-info/licenses/LICENSE
uniformbands-0.1.0.dist-info/METADATA
uniformbands-0.1.0.dist-info/WHEEL
uniformbands-0.1.0.dist-info/top_level.txt
uniformbands-0.1.0.dist-info/RECORD
