Metadata-Version: 2.4
Name: uniformbands
Version: 0.1.0
Summary: Uniform confidence bands with theoretical covering guarantees
Author-email: Félix Laplante <felixlaplante0@proton.me>
Project-URL: Source, https://gitlab.com/felixlaplante0/uniformbands
Classifier: Programming Language :: Python :: 3
Classifier: Operating System :: POSIX :: Linux
Classifier: Operating System :: MacOS
Classifier: Operating System :: Microsoft :: Windows
Requires-Python: >=3.10
License-File: LICENSE
Requires-Dist: numpy
Requires-Dist: scipy
Dynamic: license-file
